docblocks/__init__.py
docblocks/cli.py
docblocks/core.py
docblocks/export/__init__.py
docblocks/export/text_exporter.py
docblocks/extraction/text_blocks.py
docblocks/io/pdf_reader.py
docblocks-0.1.1.dist-info/licenses/LICENSE
docblocks-0.1.1.dist-info/METADATA
docblocks-0.1.1.dist-info/WHEEL
docblocks-0.1.1.dist-info/top_level.txt
docblocks-0.1.1.dist-info/RECORD
