Metadata-Version: 2.4
Name: docblocks
Version: 0.1.1
Summary: PDF to structured text with page segmentation
Author: Vishal
License-Expression: MIT
Project-URL: Homepage, https://github.com/vishalp-dev24/docblocks
Project-URL: Issues, https://github.com/vishalp-dev24/docblocks/issues
Requires-Python: >=3.8
License-File: LICENSE
Requires-Dist: pymupdf>=1.23.0
Dynamic: license-file
